rtl/reg_file.v
module regfile64 (
    input  logic        clk,        // Clock
    input  logic        reset,      // Reset signal
    input  logic        we,         // Write Enable
    input  logic [4:0]  rs1,        // Source register 1 index
    input  logic [4:0]  rs2,        // Source register 2 index
    input  logic [4:0]  rd,         // Destination register index
    input  logic [63:0] wd,         // Write Data
    output logic [63:0] rd1,        // Read Data 1
    output logic [63:0] rd2         // Read Data 2
);

    logic [63:0] regs[31:0];



    // Reset and write logic
    always_ff @(posedge clk or posedge reset) begin
        if (reset) begin
            for (int i = 0; i < 32; i++) begin
                regs[i] <= 64'd0;
            end
        end else if (we && rd != 5'd0) begin
            regs[rd] <= wd;
        end
    end

    assign rd1 = regs[rs1];
    assign rd2 = regs[rs2];

endmodule

/*
always_ff @(posedge clk) begin
  if (reset == 1) begin
    rs1 <= 5'd0;
    rs2 <= 5'd0;
    we <= 0;
  end else begin
    rs1 <= 5'd1;
    rs2 <= 5'd1;
    we <= 1;
end
*/


/*
module(
    input clk,
    input reset,
    input count,
    input rd,
    input wrt,
    input [31:0] rgstr1,
    input [31:0] rgstr2,
    output result
);
*/

reg_file.vcd
$version Generated by VerilatedVcd $end
$timescale 1ps $end
 $scope module TOP $end
  $var wire 1 d clk $end
  $var wire 1 e reset $end
  $var wire 1 f we $end
  $var wire 5 g rs1 [4:0] $end
  $var wire 5 h rs2 [4:0] $end
  $var wire 5 i rd [4:0] $end
  $var wire 64 j wd [63:0] $end
  $var wire 64 l rd1 [63:0] $end
  $var wire 64 n rd2 [63:0] $end
  $scope module regfile64 $end
   $var wire 1 d clk $end
   $var wire 1 e reset $end
   $var wire 1 f we $end
   $var wire 5 g rs1 [4:0] $end
   $var wire 5 h rs2 [4:0] $end
   $var wire 5 i rd [4:0] $end
   $var wire 64 j wd [63:0] $end
   $var wire 64 l rd1 [63:0] $end
   $var wire 64 n rd2 [63:0] $end
   $var wire 64 # regs[0] [63:0] $end
   $var wire 64 % regs[1] [63:0] $end
   $var wire 64 ' regs[2] [63:0] $end
   $var wire 64 ) regs[3] [63:0] $end
   $var wire 64 + regs[4] [63:0] $end
   $var wire 64 - regs[5] [63:0] $end
   $var wire 64 / regs[6] [63:0] $end
   $var wire 64 1 regs[7] [63:0] $end
   $var wire 64 3 regs[8] [63:0] $end
   $var wire 64 5 regs[9] [63:0] $end
   $var wire 64 7 regs[10] [63:0] $end
   $var wire 64 9 regs[11] [63:0] $end
   $var wire 64 ; regs[12] [63:0] $end
   $var wire 64 = regs[13] [63:0] $end
   $var wire 64 ? regs[14] [63:0] $end
   $var wire 64 A regs[15] [63:0] $end
   $var wire 64 C regs[16] [63:0] $end
   $var wire 64 E regs[17] [63:0] $end
   $var wire 64 G regs[18] [63:0] $end
   $var wire 64 I regs[19] [63:0] $end
   $var wire 64 K regs[20] [63:0] $end
   $var wire 64 M regs[21] [63:0] $end
   $var wire 64 O regs[22] [63:0] $end
   $var wire 64 Q regs[23] [63:0] $end
   $var wire 64 S regs[24] [63:0] $end
   $var wire 64 U regs[25] [63:0] $end
   $var wire 64 W regs[26] [63:0] $end
   $var wire 64 Y regs[27] [63:0] $end
   $var wire 64 [ regs[28] [63:0] $end
   $var wire 64 ] regs[29] [63:0] $end
   $var wire 64 _ regs[30] [63:0] $end
   $var wire 64 a regs[31] [63:0] $end
   $scope module unnamedblk1 $end
    $var wire 32 c i [31:0] $end
   $upscope $end
  $upscope $end
 $upscope $end
$enddefinitions $end


#0
b0000000000000000000000000000000000000000000000000000000000000000 #
b0000000000000000000000000000000000000000000000000000000000000000 %
b0000000000000000000000000000000000000000000000000000000000000000 '
b0000000000000000000000000000000000000000000000000000000000000000 )
b0000000000000000000000000000000000000000000000000000000000000000 +
b0000000000000000000000000000000000000000000000000000000000000000 -
b0000000000000000000000000000000000000000000000000000000000000000 /
b0000000000000000000000000000000000000000000000000000000000000000 1
b0000000000000000000000000000000000000000000000000000000000000000 3
b0000000000000000000000000000000000000000000000000000000000000000 5
b0000000000000000000000000000000000000000000000000000000000000000 7
b0000000000000000000000000000000000000000000000000000000000000000 9
b0000000000000000000000000000000000000000000000000000000000000000 ;
b0000000000000000000000000000000000000000000000000000000000000000 =
b0000000000000000000000000000000000000000000000000000000000000000 ?
b0000000000000000000000000000000000000000000000000000000000000000 A
b0000000000000000000000000000000000000000000000000000000000000000 C
b0000000000000000000000000000000000000000000000000000000000000000 E
b0000000000000000000000000000000000000000000000000000000000000000 G
b0000000000000000000000000000000000000000000000000000000000000000 I
b0000000000000000000000000000000000000000000000000000000000000000 K
b0000000000000000000000000000000000000000000000000000000000000000 M
b0000000000000000000000000000000000000000000000000000000000000000 O
b0000000000000000000000000000000000000000000000000000000000000000 Q
b0000000000000000000000000000000000000000000000000000000000000000 S
b0000000000000000000000000000000000000000000000000000000000000000 U
b0000000000000000000000000000000000000000000000000000000000000000 W
b0000000000000000000000000000000000000000000000000000000000000000 Y
b0000000000000000000000000000000000000000000000000000000000000000 [
b0000000000000000000000000000000000000000000000000000000000000000 ]
b0000000000000000000000000000000000000000000000000000000000000000 _
b0000000000000000000000000000000000000000000000000000000000000000 a
b00000000000000000000000000000000 c
0d
1e
0f
b00000 g
b00000 h
b00000 i
b0000000000000000000000000000000000000000000000000000000000000000 j
b0000000000000000000000000000000000000000000000000000000000000000 l
b0000000000000000000000000000000000000000000000000000000000000000 n
#1
b00000000000000000000000000100000 c
1d
#2
0d
0e
1f
b00001 i
b0001000100010001000100010001000100010001000100010001000100010001 j
#3
b0001000100010001000100010001000100010001000100010001000100010001 %
1d
#4
0d
0f
#5
1d
#6
0d
1f
b00010 i
b0010001000100010001000100010001000100010001000100010001000100010 j
#7
b0010001000100010001000100010001000100010001000100010001000100010 '
1d
#8
0d
0f
#9
1d
#10
0d
1f
b00011 i
b0011001100110011001100110011001100110011001100110011001100110011 j
#11
b0011001100110011001100110011001100110011001100110011001100110011 )
1d
#12
0d
0f
#13
1d
#14
0d
1f
b00100 i
b0100010001000100010001000100010001000100010001000100010001000100 j
#15
b0100010001000100010001000100010001000100010001000100010001000100 +
1d
#16
0d
0f
#17
1d
#18
0d
1f
b00101 i
b0101010101010101010101010101010101010101010101010101010101010101 j
#19
b0101010101010101010101010101010101010101010101010101010101010101 -
1d
#20
0d
0f
#21
1d
#22
0d
1f
b00110 i
b0110011001100110011001100110011001100110011001100110011001100110 j
#23
b0110011001100110011001100110011001100110011001100110011001100110 /
1d
#24
0d
0f
#25
1d
#26
0d
1f
b00111 i
b0111011101110111011101110111011101110111011101110111011101110111 j
#27
b0111011101110111011101110111011101110111011101110111011101110111 1
1d
#28
0d
0f
#29
1d
#30
0d
1f
b00000 i
b1111111111111111111111111111111111111111111111111111111111111111 j
#31
1d
#32
0d
0f
#33
1d
#34
0d
b00001 g
b00010 h
b0001000100010001000100010001000100010001000100010001000100010001 l
b0010001000100010001000100010001000100010001000100010001000100010 n
#35
1d
#36
0d
b00011 g
b00100 h
b0011001100110011001100110011001100110011001100110011001100110011 l
b0100010001000100010001000100010001000100010001000100010001000100 n
#37
1d
#38
0d
b00101 g
b00110 h
b0101010101010101010101010101010101010101010101010101010101010101 l
b0110011001100110011001100110011001100110011001100110011001100110 n
#39
1d
#40
0d
b00111 g
b00000 h
b0111011101110111011101110111011101110111011101110111011101110111 l
b0000000000000000000000000000000000000000000000000000000000000000 n
